README.txt
setup.py
data_augmentation/__init__.py
data_augmentation/pic_aug.py
data_processe/__init__.py
data_processe/compute_mean.py
data_processe/divide_train_test.py
data_processe/pachong.py
data_processe/pachong_google.py
logger/__init__.py
logger/cuda_monitor.py
logger/log_sample.py
logger/set_logger.py
model/__init__.py
model/model_init.py
visualization/__init__.py
visualization/aug_image.py
visualization/heatmap.py
xjm.egg-info/PKG-INFO
xjm.egg-info/SOURCES.txt
xjm.egg-info/dependency_links.txt
xjm.egg-info/top_level.txt