Metadata-Version: 2.1
Name: xjm
Version: 0.0.4
Summary: some fundamental functions, such as visualization,       data split, Web image crawler, etc
Home-page: UNKNOWN
Author: Jimmy
Author-email: 1150213628@qq.com
License: UNKNOWN
Platform: UNKNOWN
